Metadata-Version: 2.1
Name: Hastebin
Version: 0.0.1
Summary: Hastebin API Wrapper
Home-page: https://github.com/xrevix/Hastebin
Author: xrevix
Author-email: <xrevix666@gmail.com>
License: MIT License
Keywords: module,Hastebin,library,package,python
Platform: UNKNOWN
Classifier: Programming Language :: Python
Classifier: Programming Language :: Python :: 3
Classifier: Programming Language :: Python :: 3.5
Classifier: Programming Language :: Python :: 3.6
Classifier: Programming Language :: Python :: 3.7
Classifier: Programming Language :: Python :: 3.8
Classifier: Programming Language :: Python :: 3.9
Classifier: Programming Language :: Python :: 3.10
